{
	"atype_id": "NormalEQ",
	"etype_id": "MidExt",
	"equip_part_covered": ["Groin","Vag","Anal","Feet"],
	"weight": "2",
	"pot_data": {
		"Cloth": 1
		},
	"attribute_change": [{
		"attribute_name": "sexy",
		"attribute_type": "max",
		"adjustor": "*",
		"adjustment": "0.7"
		
	},
	{
		"attribute_name": "weak",
		"attribute_type": "max",
		"adjustor": "+",
		"adjustment": "15"
	},
	{
		"attribute_name": "dirt",
		"attribute_type": "min",
		"adjustor": "+",
		"adjustment": "50"
	},
	{
		"attribute_name": "def_plus",
		"attribute_type": "max",
		"adjustor": "+",
		"adjustment": "2"
	},
	{
		"attribute_name": "scoutcraft_plus",
		"attribute_type": "max",
		"adjustor": "+",
		"adjustment": "1"
	},
	{
		"attribute_name": "move_speed",
		"attribute_type": "max",
		"adjustor": "-",
		"adjustment": "0.1"
	},
	{
		"attribute_name": "dodge_frame",
		"attribute_type": "max",
		"adjustor": "-",
		"adjustment": "2"
	}
	]
}